Metadata-Version: 2.1
Name: fileselector
Version: 1.0.4
Summary: A Python package that prints all files in a specified folder whick can be selected by the user.
Home-page: UNKNOWN
Author: TheAPEX, Greg M
Author-email: greg@ap3x.xyz
License: MIT
Platform: UNKNOWN
Classifier: License :: OSI Approved :: MIT License
Classifier: Programming Language :: Python :: 3.7
